dgspoc/__init__.py
dgspoc/__main__.py
dgspoc/adaptor.py
dgspoc/batch.py
dgspoc/config.py
dgspoc/constant.py
dgspoc/core.py
dgspoc/dotxml.py
dgspoc/example.py
dgspoc/exampledata.yaml
dgspoc/exceptions.py
dgspoc/interpreter.py
dgspoc/main.py
dgspoc/operation.py
dgspoc/parser.py
dgspoc/report.py
dgspoc/robotframeworklib.py
dgspoc/storage.py
dgspoc/usage.py
dgspoc/utils.py
dgspoc-0.3.10.1.dist-info/LICENSE
dgspoc-0.3.10.1.dist-info/METADATA
dgspoc-0.3.10.1.dist-info/WHEEL
dgspoc-0.3.10.1.dist-info/entry_points.txt
dgspoc-0.3.10.1.dist-info/top_level.txt
dgspoc-0.3.10.1.dist-info/RECORD
